amazon/__init__.py
amazon/_modidx.py
amazon/client.py
amazon/config.py
amazon/crypto.py
amazon_python-0.0.11.dist-info/licenses/LICENSE
amazon_python-0.0.11.dist-info/METADATA
amazon_python-0.0.11.dist-info/WHEEL
amazon_python-0.0.11.dist-info/entry_points.txt
amazon_python-0.0.11.dist-info/top_level.txt
amazon_python-0.0.11.dist-info/RECORD
